pulumi_auth0/__init__.py
pulumi_auth0/_inputs.py
pulumi_auth0/_utilities.py
pulumi_auth0/action.py
pulumi_auth0/attack_protection.py
pulumi_auth0/branding.py
pulumi_auth0/branding_phone_notification_template.py
pulumi_auth0/branding_theme.py
pulumi_auth0/client.py
pulumi_auth0/client_credentials.py
pulumi_auth0/client_grant.py
pulumi_auth0/connection.py
pulumi_auth0/connection_client.py
pulumi_auth0/connection_clients.py
pulumi_auth0/connection_directory.py
pulumi_auth0/connection_keys.py
pulumi_auth0/connection_profile.py
pulumi_auth0/connection_scim_configuration.py
pulumi_auth0/connection_scim_token.py
pulumi_auth0/custom_domain.py
pulumi_auth0/custom_domain_verification.py
pulumi_auth0/email_provider.py
pulumi_auth0/email_template.py
pulumi_auth0/encryption_key_manager.py
pulumi_auth0/event_stream.py
pulumi_auth0/flow.py
pulumi_auth0/flow_vault_connection.py
pulumi_auth0/form.py
pulumi_auth0/get_action.py
pulumi_auth0/get_attack_protection.py
pulumi_auth0/get_branding.py
pulumi_auth0/get_branding_phone_notification_template.py
pulumi_auth0/get_branding_theme.py
pulumi_auth0/get_client.py
pulumi_auth0/get_client_grants.py
pulumi_auth0/get_clients.py
pulumi_auth0/get_connection.py
pulumi_auth0/get_connection_directory.py
pulumi_auth0/get_connection_directory_default_mapping.py
pulumi_auth0/get_connection_keys.py
pulumi_auth0/get_connection_profile.py
pulumi_auth0/get_connection_scim_configuration.py
pulumi_auth0/get_custom_domain.py
pulumi_auth0/get_custom_domains.py
pulumi_auth0/get_event_stream.py
pulumi_auth0/get_flow.py
pulumi_auth0/get_flow_vault_connection.py
pulumi_auth0/get_form.py
pulumi_auth0/get_network_acl.py
pulumi_auth0/get_organization.py
pulumi_auth0/get_outbound_ips.py
pulumi_auth0/get_pages.py
pulumi_auth0/get_phone_notification_template.py
pulumi_auth0/get_phone_provider.py
pulumi_auth0/get_prompt_screen_partials.py
pulumi_auth0/get_prompt_screen_renderer.py
pulumi_auth0/get_resource_server.py
pulumi_auth0/get_role.py
pulumi_auth0-3.37.0.dist-info/METADATA
pulumi_auth0-3.37.0.dist-info/WHEEL
pulumi_auth0-3.37.0.dist-info/top_level.txt
pulumi_auth0-3.37.0.dist-info/RECORD
